pandasnotebooks/__init__.py
pandasnotebooks/_filter.py
pandasnotebooks/_latex.py
pandasnotebooks/_loader.py
pandasnotebooks/_plot.py
pandasnotebooks-0.4.1.dist-info/WHEEL
pandasnotebooks-0.4.1.dist-info/METADATA
pandasnotebooks-0.4.1.dist-info/RECORD
