Metadata-Version: 2.1
Name: pandasnotebooks
Version: 0.4.1
Summary: Widgets to analyze, manipulate dataframes from dbispipelines.
License: GPL-3.0+
Author: Benjamin Murauer
Author-email: b.murauer@posteo.de
Requires-Python: >=3.6.1,<4.0.0
Classifier: License :: OSI Approved :: GNU General Public License v3 or later (GPLv3+)
Classifier: Programming Language :: Python :: 3
Classifier: Programming Language :: Python :: 3.7
Classifier: Programming Language :: Python :: 3.8
Classifier: Programming Language :: Python :: 3.9
Requires-Dist: dbispipeline (>=0.8.0,<0.9.0)
Requires-Dist: ipywidgets (>=7.5.1,<8.0.0)
Requires-Dist: pandas (>=1.1.1,<2.0.0)
